color_correction_asdfghjkl/__init__.py
color_correction_asdfghjkl/py.typed
color_correction_asdfghjkl/constant/color_checker.py
color_correction_asdfghjkl/constant/yolov8_det.py
color_correction_asdfghjkl/core/card_detection/base.py
color_correction_asdfghjkl/core/card_detection/mcc_det.py
color_correction_asdfghjkl/core/card_detection/yolov8_det_onnx.py
color_correction_asdfghjkl/core/correction/base.py
color_correction_asdfghjkl/core/correction/least_squares.py
color_correction_asdfghjkl/schemas/device.py
color_correction_asdfghjkl/schemas/yolov8_det.py
color_correction_asdfghjkl/services/color_correction.py
color_correction_asdfghjkl/utils/__init__.py
color_correction_asdfghjkl/utils/device_info.py
color_correction_asdfghjkl/utils/downloader.py
color_correction_asdfghjkl/utils/geometry_processing.py
color_correction_asdfghjkl/utils/image_processing.py
color_correction_asdfghjkl/utils/yolo_utils.py
color_correction_asdfghjkl-0.0.1a2.dist-info/METADATA
color_correction_asdfghjkl-0.0.1a2.dist-info/WHEEL
color_correction_asdfghjkl-0.0.1a2.dist-info/RECORD
