Metadata-Version: 2.4
Name: color-correction-asdfghjkl
Version: 0.0.1a2
Summary: help to do color correction on images based on color checker card classic 24 patch.
Project-URL: Repository, https://github.com/agfianf/color-correction-asdfghjkl
Project-URL: Issues, https://github.com/agfianf/color-correction-asdfghjkl/issues
Author-email: magfianf <muhammadagfian96@gmail.com>
Keywords: color consistency,color correction,color-consistency,color-correction
Classifier: Operating System :: OS Independent
Classifier: Programming Language :: Python :: 3 :: Only
Classifier: Programming Language :: Python :: 3.10
Classifier: Programming Language :: Python :: 3.11
Classifier: Programming Language :: Python :: 3.12
Classifier: Typing :: Typed
Requires-Python: >=3.10
Requires-Dist: colour-science>=0.4.6
Requires-Dist: httpx>=0.28.1
Requires-Dist: pydantic-settings>=2.7.1
Requires-Dist: pydantic>=2.10.5
Requires-Dist: shapely>=2.0.6
